DiscordEconomy/__init__.py
DiscordEconomy/__version__.py
DiscordEconomy/economy.py
DiscordEconomy/exceptions.py
DiscordEconomy/objects.py
DiscordEconomy/MongoDB/__init__.py
DiscordEconomy/Sqlite/__init__.py
DiscordEconomy-1.3.8.dist-info/LICENSE
DiscordEconomy-1.3.8.dist-info/METADATA
DiscordEconomy-1.3.8.dist-info/WHEEL
DiscordEconomy-1.3.8.dist-info/top_level.txt
DiscordEconomy-1.3.8.dist-info/RECORD
