Metadata-Version: 2.1
Name: DiscordEconomy
Version: 1.3.8
Summary: Discord.py, other libs(hikari etc.), and forks(pycord, nextcord etc.) extension to create economy easily with support of Sqlite/MongoDB.
Home-page: https://github.com/Nohet/DiscordEconomy
Author: Nohet
Author-email: igorczupryniak503@gmail.com
License: MIT
Keywords: discord,discord extension,discord.py,economy,economy bot,discord economy,DiscordEconomy
Classifier: Development Status :: 5 - Production/Stable
Classifier: Intended Audience :: Developers
Classifier: License :: OSI Approved :: MIT License
Classifier: Programming Language :: Python :: 3
License-File: LICENSE
Requires-Dist: aiosqlite
Requires-Dist: aiohttp
Requires-Dist: motor
Requires-Dist: dnspython
Requires-Dist: nest-asyncio
